{
  "0": "North Norfolk Railway",
  "1": "Citadelle de Qu%C3%A9bec",
  "2": "White Cliffs of Dover",
  "3": "Paseo del Prado, Madrid",
  "4": "Tuileries Garden",
  "5": "Le Reculet",
  "6": "Pra%C3%A7a do Com%C3%A9rcio",
  "7": "Santu%C3%A1rio de F%C3%A1tima",
  "8": "Charles Bridge",
  "9": "Batenburg Castle",
  "10": "University of Chicago Library",
  "11": "La Boca, Buenos Aires",
  "12": "Grampians National Park",
  "13": "Agra Fort",
  "14": "Lake Anna State Park",
  "15": "Old Town (Skopje)",
  "16": "Chernihiv Collegium",
  "17": "Stonehenge",
  "18": "Media contributed by the ETH-Bibliothek",
  "19": "Botanical Garden Jevremovac",
  "20": "Attabad Lake",
  "21": "Mus%C3%A9e Bolo",
  "22": "Gr%C3%B6den",
  "23": "Port of Casablanca",
  "24": "Castle of Visegr%C3%A1d",
  "25": "Enz",
  "26": "High Bridge Trail State Park",
  "27": "Poltava's city park",
  "28": "Bryce Canyon National Park",
  "29": "Novodevichy cemetery (Moscow)",
  "30": "Forest of Dean",
  "31": "Akkerman fortress",
  "32": "Zuid-Kennemerland",
  "33": "Sarmizegetusa Regia",
  "34": "Fichtelberg (Erzgebirge)",
  "35": "Schloss Gro%C3%9Fkmehlen",
  "36": "River Mersey",
  "37": "John D. Rockefeller Jr. Library",
  "38": "Isa Khan Niyazi's tomb",
  "39": "Madikwe Game Reserve",
  "40": "Lewis Ginter Botanical Garden",
  "41": "Mason Neck State Park",
  "42": "Itmad-Ud-Daulah's Tomb",
  "43": "Santa Maria Magdalena Parish Church of Magdalena",
  "44": "Pazo de Oca",
  "45": "Schloss Rosegg",
  "46": "Ch%C3%A2teau d'Azay-le-Rideau",
  "47": "Duisitzkarsee",
  "48": "Beaumaris Castle",
  "49": "Aurangabad Caves",
  "50": "Abbey of Mont Saint-Michel",
  "51": "Royal Palace of Amsterdam",
  "52": "Cimitero di Staglieno (Genoa)",
  "53": "PNC Park",
  "54": "Tropenmuseum Amsterdam",
  "55": "T%C3%A4by kyrka",
  "56": "Bois de Boulogne",
  "57": "Church of the Ascension of Christ (Skopje)",
  "58": "Wat Saket",
  "59": "Langweerderwielen-Langwarder Wielen",
  "60": "Perge",
  "61": "French Quarter",
  "62": "Xalapa Anthropology Museum",
  "63": "Brockhampton Estate",
  "64": "P%C4%99ksowy Brzyzek National Cemetery in Zakopane",
  "65": "Occoneechee State Park",
  "66": "Majorelle Garden",
  "67": "Wang Family Compound",
  "68": "Dominican church, Lviv",
  "69": "Conisbrough Castle",
  "70": "M%C3%BCritz-Nationalpark",
  "71": "Tara Mountain",
  "72": "Jaffa Clock Tower",
  "73": "Sninsk%C3%BD kame%C5%88",
  "74": "Nieuwe Waterweg",
  "75": "Lake Garda",
  "76": "Kongsfjorden",
  "77": "Ca%C3%B1%C3%B3n del Sumidero",
  "78": "Matka Canyon",
  "79": "Souq Waqif",
  "80": "Haghpat",
  "81": "Markiezenhof",
  "82": "Shivta",
  "83": "Lahore Museum",
  "84": "Pinacoteca del Castello Sforzesco",
  "85": "Kilmallie",
  "86": "Fresh Meadows, Queens",
  "87": "Dormition Cathedral, Kharkiv",
  "88": "Saint John the Baptist Church (Calumpit, Bulacan)",
  "89": "Grand Canyon",
  "90": "Taillefer",
  "91": "St. Gayane",
  "92": "Nimrod Fortress",
  "93": "Church of the Annunciation",
  "94": "Kostel Panny Marie V%C3%ADt%C4%9Bzn%C3%A9 (B%C3%ADl%C3%A1 Hora)",
  "95": "Mardale",
  "96": "%C3%87ufut Qale",
  "97": "Museu de Marinha de Lisboa",
  "98": "Stearns Wharf",
  "99": "Naturpark Bayerischer Wald",
  "100": "North Sea",
  "101": "C%C3%A2r%C8%9Ba monastery",
  "102": "Museum of Folk Architecture and Ethnography in Pyrohiv",
  "103": "Beagle Channel",
  "104": "Kwun Tong",
  "105": "Canal Park, Duluth",
  "106": "Stadhuis Nijmegen",
  "107": "Palazzo Ducale (Genoa)",
  "108": "Episcopal Diocese of Southwest Florida",
  "109": "Stadhuis Middelburg",
  "110": "Leninsky Prospekt (Moscow)",
  "111": "Nationaal Militair Museum",
  "112": "Velebit",
  "113": "Bhawal National Park",
  "114": "Aiguamolls de l'Empord%C3%A0",
  "115": "Castel Sant'Angelo (Rome)",
  "116": "Akashi Kaikyo National Government Park",
  "117": "Parque de Pradolongo",
  "118": "Zorats Karer",
  "119": "Helf%C5%A1t%C3%BDn",
  "120": "Osaka Prefectural Flower Garden",
  "121": "Spring Grove Cemetery, Cincinnati",
  "122": "Great Sand Dunes National Park",
  "123": "Pe%C5%A1ter",
  "124": "Gas Works Park",
  "125": "West Side Market",
  "126": "Akhtala monastery",
  "127": "York River State Park",
  "128": "Mljet",
  "129": "Preah Khan",
  "130": "Terra Botanica",
  "131": "Externsteine",
  "132": "Rocky Mountain National Park",
  "133": "Castle Doorwerth",
  "134": "Bantayog ng mga Bayani",
  "135": "Sri Lanka",
  "136": "Dhanmondi Shahi Eidgah",
  "137": "Saxon Switzerland",
  "138": "Antikenmuseum der Universit%C3%A4t Heidelberg",
  "139": "Elektrociep%C5%82ownia Szombierki",
  "140": "Serra da Estrela",
  "141": "Pingyao",
  "142": "Saghmosavank",
  "143": "Church of Our Lady in front of T%C3%BDn",
  "144": "Schloss Oberwerries",
  "145": "Trevi fountain",
  "146": "Haleakal%C4%81 National Park",
  "147": "Menkemaborg, Uithuizen",
  "148": "Niedzica Castle",
  "149": "Botanical Garden KIT",
  "150": "Sassi di Matera",
  "151": "Kasteel Amerongen",
  "152": "Cop%C3%A1n",
  "153": "Bassin de Latone",
  "154": "Parque Nacional de Ordesa y Monte Perdido",
  "155": "Fomin Botanical Garden",
  "156": "Princes Street Gardens",
  "157": "Sheung Wan",
  "158": "La D%C3%B4le",
  "159": "Hills of Dumfries and Galloway",
  "160": "Chersonesos Taurica",
  "161": "San Guillermo Church, Bacolor",
  "162": "Olympiastadion Berlin",
  "163": "Bara Imambara",
  "164": "Palanok castle",
  "165": "Westmoreland State Park",
  "166": "Kinderdijk windmills",
  "167": "Sevanavank",
  "168": "Natural Tunnel State Park",
  "169": "City of David",
  "170": "Illa de Ons",
  "171": "Uzhhorod castle",
  "172": "Ocean Park, Hong Kong",
  "173": "Sajek",
  "174": "Pont du Gard",
  "175": "Cheung Chau",
  "176": "Khor Virap",
  "177": "Sete Cidades",
  "178": "Svirzh Castle",
  "179": "Shenandoah River State Park",
  "180": "Mesa Verde National Park",
  "181": "Greenwich Cemetery",
  "182": "Southern Upland Way",
  "183": "Niagara Falls",
  "184": "%C5%BD%C3%A1rsk%C3%BD rybn%C3%ADk",
  "185": "Hardt, Wuppertal",
  "186": "Jurassic Coast",
  "187": "Cathedral of Yerevan",
  "188": "Deutsches Theater Berlin",
  "189": "Pohick Creek",
  "190": "Lviv",
  "191": "Staatliches Museum f%C3%BCr Arch%C3%A4ologie Chemnitz",
  "192": "Schloss Sonnenstein",
  "193": "Poipu Beach Park",
  "194": "Diocesan Shrine and Parish of the Immaculate Conception of Naic",
  "195": "Chester city walls",
  "196": "Museu de Arqueologia e Etnologia da Universidade de S%C3%A3o Paulo",
  "197": "Tughlaqabad Fort",
  "198": "Tsukiji fish market",
  "199": "Brighton West Pier",
  "200": "Metro Kino",
  "201": "Gorges du Verdon",
  "202": "Gotthard Base Tunnel",
  "203": "Cloister of Saint-Trophime (Arles)",
  "204": "Parque Estadual da Serra do Mar",
  "205": "Enchanted Floral Gardens of Kula",
  "206": "Sundarbans",
  "207": "James River State Park",
  "208": "Cathedral of Talin",
  "209": "Usa Shrine",
  "210": "Corktown, Toronto",
  "211": "Kaptai Lake",
  "212": "Metairie Cemetery",
  "213": "Cliffs of Moher",
  "214": "Lake Thun",
  "215": "Hildener Heide",
  "216": "Uluru",
  "217": "Denali",
  "218": "Southwest Virginia Museum Historical State Park",
  "219": "Minerals of Naica",
  "220": "Lindisfarne",
  "221": "Botanical garden in Kryvyi Rih",
  "222": "Calanques of Marseille",
  "223": "Breitachklamm",
  "224": "St. Volodymyr's Cathedral",
  "225": "Oslofjorden",
  "226": "Lake Maggiore",
  "227": "Zonnestraal, Hilversum",
  "228": "Begnas Lake",
  "229": "Wollaton Hall",
  "230": "Sea of Galilee",
  "231": "Shuanglin Temple (Pingyao)",
  "232": "Etnographic Museum in Belgrade",
  "233": "Rufino Tamayo Museum of Pre Hispanic Art",
  "234": "Huwenowsee",
  "235": "Katzrin ancient village",
  "236": "K%C5%8Draku-en",
  "237": "Pakistan Monument Islamabad",
  "238": "Festung Marienberg",
  "239": "H%C3%B4pital Notre-Dame %C3%A0 la Rose",
  "240": "C%C4%93sis Castle",
  "241": "Bakhchisaray Palace",
  "242": "Shwedagon pagoda",
  "243": "Parc Angrignon",
  "244": "Hall of Mirrors (Palace of Versailles)",
  "245": "Oostvaardersplassen",
  "246": "Theatro Municipal de S%C3%A3o Paulo",
  "247": "Armenian Quarter, Jerusalem",
  "248": "Schloss Weilburg",
  "249": "Gateway of India",
  "250": "Samara",
  "251": "Purana Qila",
  "252": "Aghjots Vank",
  "253": "Stratford-upon-Avon Canal",
  "254": "Stafford Air %26 Space Museum",
  "255": "Kiautschou",
  "256": "Eliasfriedhof, Dresden",
  "257": "Golden Gate Bridge",
  "258": "Columbarium of the P%C3%A8re-Lachaise Cemetery",
  "259": "Ogrodzieniec Castle",
  "260": "Port of London",
  "261": "Ingleborough",
  "262": "Chrysi (Island)",
  "263": "Campo del Moro",
  "264": "Mother Teresa Memorial Home (Skopje)",
  "265": "Dwarves in Wroc%C5%82aw",
  "266": "Brighton Pier",
  "267": "Sannomiya, Kobe",
  "268": "Sal%C3%A8ve",
  "269": "Tarakanivskiy fort",
  "270": "Pozna%C5%84 Stare Zoo",
  "271": "Su Nuraxi (Barumini)",
  "272": "Naturschutzgebiet Mittleres Innerstetal mit Kanstein",
  "273": "Genoese fortress (Sudak)",
  "274": "Taj Mahal, Bhopal",
  "275": "Belle Isle State Park (Virginia)",
  "276": "Murnauer Moos",
  "277": "Wheat",
  "278": "Jewellery",
  "279": "Kardzhali History Museum",
  "280": "Glacier National Park",
  "281": "Victoria %26 Alfred Waterfront",
  "282": "Dupont Circle",
  "283": "Hubschraubermuseum B%C3%BCckeburg",
  "284": "Smolensk Kremlin",
  "285": "Church of Elijah the Prophet in Yaroslavl",
  "286": "James Gardens",
  "287": "Volodymyrskyi Park",
  "288": "Church of the Intercession (Parkhomovka)",
  "289": "Wadi Rum",
  "290": "Downtown Pittsburgh",
  "291": "Porta Soprana (Genoa)",
  "292": "City of San Fernando, Pampanga",
  "293": "Wulingyuan",
  "294": "Muskau Park",
  "295": "Ponte da Arr%C3%A1bida",
  "296": "Flower Festival Commemorative Park",
  "297": "Aali Qapu",
  "298": "SBB Historic",
  "299": "Rievaulx Abbey",
  "300": "Mir Castle Complex",
  "301": "Lake Pamvotis",
  "302": "Silos",
  "303": "Helg%C3%B8ya, Hedmark",
  "304": "Rizal Memorial Coliseum",
  "305": "Badlands National Park",
  "306": "Calderstones Park",
  "307": "Danube Biosphere Reserve in Ukraine",
  "308": "Tsiranavor",
  "309": "Graceland",
  "310": "Madrid R%C3%ADo",
  "311": "Alte Leine",
  "312": "Perperikon",
  "313": "Soos",
  "314": "Daulatabad, Maharashtra",
  "315": "Swiss National Park",
  "316": "Douthat State Park",
  "317": "Horezu Monastery",
  "318": "Kerch Archeology museum",
  "319": "Shrine Mont",
  "320": "St. Hripsime church in Vagharshapat",
  "321": "Cathedral of the Dormition of the Theotokos (Vladimir)",
  "322": "Ljubljana Castle",
  "323": "Guggenheim Museum Bilbao",
  "324": "First Landing State Park",
  "325": "Noraduz Cemetery",
  "326": "Ibitipoca",
  "327": "Vodno",
  "328": "Taipa",
  "329": "Wat Pho",
  "330": "Yad Vashem",
  "331": "Llangollen Canal",
  "332": "Villa Poppaea (Torre Annunziata)",
  "333": "Forth Bridge",
  "334": "Powhatan State Park",
  "335": "Kasteel van Breda",
  "336": "Central Park",
  "337": "Burrator",
  "338": "Chongwu City",
  "339": "Sydney Harbour Bridge",
  "340": "Sanya Bay",
  "341": "Jantar Mantar (Delhi)",
  "342": "Jewish Quarter, Jerusalem",
  "343": "Castle Heeswijk",
  "344": "House with Chimeras (Kiev)",
  "345": "Chippokes Plantation State Park",
  "346": "United States National Arboretum",
  "347": "Binondo Church",
  "348": "Stelvio National Park",
  "349": "Gorgany Nature Reserve",
  "350": "Atomium",
  "351": "Pirin",
  "352": "Museo Etnogr%C3%A1fico de Cantabria",
  "353": "Clandestine Immigration and Naval Museum, Haifa",
  "354": "Feofaniya Park",
  "355": "De Alde Feanen",
  "356": "River Severn",
  "357": "Monument to Bohdan Khmelnytsky in Kiev by Mikhail Mikeshin",
  "358": "Dujiangyan",
  "359": "Kyffh%C3%A4userdenkmal",
  "360": "Bosque de Tlalpan",
  "361": "Koyasan",
  "362": "Dead Sea",
  "363": "Museum of Yugoslavia",
  "364": "Onze Lieve Vrouwe Kerk, Kampen",
  "365": "Zentrum Paul Klee",
  "366": "Kantanagar Temple",
  "367": "Mathura Museum",
  "368": "Barrow Hill Engine Shed",
  "369": "Graslei",
  "370": "Craters of the Moon National Monument",
  "371": "Br%C3%BChl's Terrace",
  "372": "Plaza Mayor, Salamanca",
  "373": "St. Martin's Island",
  "374": "Lake Como",
  "375": "Tsiranavor church of Avan",
  "376": "Grote of Sint-Bartholomeuskerk (Schoonhoven)",
  "377": "Brompton Cemetery",
  "378": "Great Wall of China at Mutianyu",
  "379": "Pele%C8%99 Castle",
  "380": "American Falls",
  "381": "Staunton River State Park",
  "382": "Petrovaradin Fortress",
  "383": "Soltaniyeh Dome",
  "384": "National M. M. Grishko botanical garden (Kiev)",
  "385": "Khotyn Fortress",
  "386": "Sacra di San Michele",
  "387": "Regent's Park",
  "388": "Czocha Castle",
  "389": "River Exe",
  "390": "Oosterscheldekering",
  "391": "Wealdway",
  "392": "Trans Pennine Trail",
  "393": "Diana Veteranorum",
  "394": "Sameba Cathedral, Tbilisi",
  "395": "Palace of Culture and Science",
  "396": "Donaukanal",
  "397": "Central park, Chernihiv",
  "398": "Anglesey Abbey",
  "399": "Jasna G%C3%B3ra",
  "400": "Schloss Rochlitz",
  "401": "Downtown Brooklyn",
  "402": "La Pedriza",
  "403": "Carvers Creek State Park",
  "404": "Financial District, Manhattan",
  "405": "Parque nacional del Teide",
  "406": "Ebenalp",
  "407": "Huangshan",
  "408": "Ashtarak Marine church",
  "409": "Rombergpark",
  "410": "Stirling Castle",
  "411": "Palacio de Bellas Artes",
  "412": "Great Smoky Mountains National Park",
  "413": "Martebo kyrka",
  "414": "Beverweerd",
  "415": "Seattle Aquarium",
  "416": "Barbican Arts Centre",
  "417": "Hauz Khas Complex",
  "418": "Museum of Philippine Political History",
  "419": "Castle Square in Warsaw",
  "420": "Staffordshire and Worcestershire Canal",
  "421": "Royal National Park",
  "422": "Museum on the demarcation line in Rokycany",
  "423": "Autostadt",
  "424": "Pillnitz Castle",
  "425": "United States National Bonsai %26 Penjing Museum",
  "426": "Sima de las Cotorras",
  "427": "Plymouth Hoe",
  "428": "Financial District, Toronto",
  "429": "Majori",
  "430": "Ahsan Manzil",
  "431": "Kronstadt Naval Cathedral",
  "432": "Naturschutzgebiet Grainberg-Kalbenstein und Saupurzel",
  "433": "Hampton Park Terrace",
  "434": "Tel Aviv Port",
  "435": "Br%C3%B3dno Cemetery",
  "436": "Mangup",
  "437": "Brest Fortress",
  "438": "Feroz Shah Kotla",
  "439": "K%C5%82odzko Fortress",
  "440": "Lancaster Canal",
  "441": "Freedom Park",
  "442": "Machu Picchu",
  "443": "Mount Arapiles",
  "444": "Lake Lucerne",
  "445": "Wayne National Forest",
  "446": "Japanese garden, Seattle",
  "447": "Al Khazneh",
  "448": "Biosphere 2",
  "449": "Dunnottar Castle",
  "450": "Hurricane Ridge",
  "451": "Loch Lomond",
  "452": "Shilin (Stone Forest)",
  "453": "Wroc%C5%82aw Old Jewish Cemetery",
  "454": "Mineralogisches Museum der Universit%C3%A4t Bonn",
  "455": "Mehrangarh Fort",
  "456": "Ronsdorfer Talsperre",
  "457": "Baba Vida Fortress",
  "458": "Nachlat Binyamin Street, Tel Aviv-Yafo",
  "459": "Parque Enrique Tierno Galv%C3%A1n",
  "460": "Ch%C3%A2teau de Vaux-le-Vicomte",
  "461": "Etosha National Park",
  "462": "St. John Kaneo Church",
  "463": "Bear Creek Lake State Park",
  "464": "San Agustin Church, Manila",
  "465": "Kosciuszko National Park",
  "466": "Goleta Beach",
  "467": "Sai Ying Pun",
  "468": "Parque Nacional da Peneda-Ger%C3%AAs",
  "469": "Olympic Stadium (London)",
  "470": "Mari%C3%A4 Himmelfahrt (Berching)",
  "471": "Donetsk botanic garden",
  "472": "Kasteel Woerden",
  "473": "Palace of Paskievi%C4%8Ds, Homie%C4%BA",
  "474": "Edinburgh Castle",
  "475": "Maui Nui Botanical Gardens",
  "476": "Castell de Montju%C3%AFc",
  "477": "Brazos Bend State Park",
  "478": "Wyrley and Essington Canal",
  "479": "Danube Delta",
  "480": "Ponte Vecchio",
  "481": "Speicherstadt",
  "482": "Parque Terra Nostra",
  "483": "Museo Malvinas e Islas del Atl%C3%A1ntico Sur",
  "484": "Hadrian's Wall",
  "485": "St. Lawrence, Toronto",
  "486": "Teatro Carlo Felice (Genoa)",
  "487": "Tsitsernakaberd",
  "488": "Dovbush rocks",
  "489": "Vittoriano (Rome)",
  "490": "Castell de la Santa B%C3%A0rbara",
  "491": "Zolochiv Castle",
  "492": "Yarkon Park",
  "493": "Bundeshaus Bern",
  "494": "Khao Sok National Park",
  "495": "Writers footways",
  "496": "Jardin du Luxembourg",
  "497": "Voskresenska church in Sumy",
  "498": "Angkor Wat",
  "499": "Western Wall Tunnel",
  "500": "V%C3%B6lklingen Ironworks",
  "501": "Chornohora range",
  "502": "Igua%C3%A7u National Park",
  "503": "Magnolia Plantation, South Carolina",
  "504": "Warangal Fort",
  "505": "Lake Mead",
  "506": "Florentin (Tel Aviv)",
  "507": "Conwy Castle",
  "508": "Cimitero Monumentale (Milan)",
  "509": "Tverskoy",
  "510": "Qutb Minar and its monuments, Delhi",
  "511": "Vondelpark",
  "512": "Qila-i-Kuhna mosque",
  "513": "Palais de l'Isle in Annecy",
  "514": "Abbaye Sainte-Marie de Lagrasse",
  "515": "Parque Estadual da Pedra da Boca",
  "516": "Lipa Cathedral",
  "517": "Muzeum In%C5%BCynierii Miejskiej w Krakowie",
  "518": "Black Mountains, Wales",
  "519": "Stan Hywet Hall and Gardens",
  "520": "Chich%C3%A9n Itz%C3%A1",
  "521": "Bigorski Monastery",
  "522": "Saint Aloysius Gonzaga Church (San Luis, Pampanga)",
  "523": "South Devon Railway sea wall in Dawlish",
  "524": "Saiful Muluk Lake",
  "525": "Yellow Flower Mound Park",
  "526": "Rio-Antirio Bridge",
  "527": "Akbari Sarai",
  "528": "Oresund Bridge",
  "529": "Grayson Highlands State Park",
  "530": "Wyperfeld National Park",
  "531": "Lagoa das Sete Cidades",
  "532": "Lake Turgoyak",
  "533": "Cambridge University Botanic Garden",
  "534": "Grotte di Toirano",
  "535": "Mehmed Pa%C5%A1a Sokolovi%C4%87 Bridge in Vi%C5%A1egrad",
  "536": "USS Hornet Museum",
  "537": "Macmillan Way",
  "538": "Capitole de Toulouse",
  "539": "Giant's Causeway",
  "540": "Bayon",
  "541": "Auschwitz concentration camp",
  "542": "Lancashire Witches Walk",
  "543": "Ar%C3%A8nes d'Arles",
  "544": "Zvartnots",
  "545": "River Farm",
  "546": "Nature reserve of Trapani and Paceco salt ponds",
  "547": "Seven Sisters, Sussex",
  "548": "Khimki Reservoir",
  "549": "Skole Beskids National Nature Park",
  "550": "Raystown Lake",
  "551": "Horseshoe Falls",
  "552": "Kanheri Caves",
  "553": "Maribor Regional Museum",
  "554": "Zollverein Coal Mine industrial complex",
  "555": "Memorial to the Murdered Jews of Europe",
  "556": "Vienna City Hall",
  "557": "Kahanu Garden",
  "558": "Aspydni slantsi",
  "559": "Kopaonik",
  "560": "Stadhuis (Dordrecht)",
  "561": "Catedral San Sebasti%C3%A1n, Cochabamba",
  "562": "Arg of Karim Khan",
  "563": "Pilkington Library",
  "564": "Way of Saint James in Spain",
  "565": "Wenceslas Square",
  "566": "Akbar's Tomb",
  "567": "Dayr-e Gachin",
  "568": "Nederlule%C3%A5 kyrka",
  "569": "Calgary",
  "570": "Lawachara National Park",
  "571": "Clearwater Beach, Florida",
  "572": "Parque Nacional de Aparados da Serra",
  "573": "Mourne Mountains",
  "574": "High Park, Toronto",
  "575": "Granhults kyrka",
  "576": "Matterhorn",
  "577": "Botanischer Garten Freiburg",
  "578": "Castelo dos Mouros",
  "579": "Sochi Arboretum",
  "580": "Parque Estadual da Ilha do Mel",
  "581": "Uluru-Kata Tjuta National Park",
  "582": "Fynbos",
  "583": "Oleksandria Park",
  "584": "Manassas National Battlefield Park",
  "585": "River Nene",
  "586": "Atar HaRiShonim BaNegev",
  "587": "Hierapolis",
  "588": "Idaho Military History Museum",
  "589": "Savannah Historic District (Savannah, Georgia)",
  "590": "Carsulae",
  "591": "Jackson Square, New Orleans",
  "592": "Monumento a la Revoluci%C3%B3n (M%C3%A9xico)",
  "593": "Moscow Raceway",
  "594": "Wawel",
  "595": "Naturschutzgebiet Schiefer Holzer Berg",
  "596": "Lednice Castle",
  "597": "Royal Tyrrell Museum",
  "598": "Oxburgh Hall",
  "599": "Qila Rai Pithora",
  "600": "Sofiyivsky Park",
  "601": "Waldfriedhof Dahlem",
  "602": "D%C5%8Dtonbori",
  "603": "El Tatio",
  "604": "National Landscape Park %C2%ABSvyati Gory%C2%BB",
  "605": "Rocks of MODR",
  "606": "Brick Lane",
  "607": "Victoria and Albert Museum of Childhood",
  "608": "Grote of Onze-Lieve-Vrouwekerk (Breda)",
  "609": "Karmravor",
  "610": "Leesylvania State Park",
  "611": "City walls of Dubrovnik",
  "612": "Caerphilly Castle",
  "613": "Corfe Castle",
  "614": "J%C3%BCdischer Friedhof Berlin-Wei%C3%9Fensee",
  "615": "Otterbein University",
  "616": "Skagit Valley Tulip Festival",
  "617": "Wales Millennium Centre",
  "618": "Spandauer Forst",
  "619": "Rock Garden, Chandigarh",
  "620": "Artgate Fondazione Cariplo",
  "621": "Lake Bled",
  "622": "Kontula",
  "623": "Pavlovsk park",
  "624": "Brockenbahn",
  "625": "Evangelische Stadtkirche Hungen",
  "626": "Birka",
  "627": "Jackson Ward",
  "628": "Crystal City, Arlington, Virginia",
  "629": "Bolton Abbey",
  "630": "Wells Gray Provincial Park",
  "631": "Edificio del ex Congreso Nacional de Chile",
  "632": "RHS Wisley",
  "633": "Mount Rainier National Park",
  "634": "Poltava Natural History Museum",
  "635": "Kazan",
  "636": "David Gareja monastery complex",
  "637": "Slot Zeist",
  "638": "Haseder Busch",
  "639": "DB Museum Koblenz-L%C3%BCtzel",
  "640": "Kenilworth Park %26 Aquatic Gardens",
  "641": "Conimbriga",
  "642": "S%C3%A3o Joaquim National Park",
  "643": "Castle of Coustaussa",
  "644": "Norfolk Coast Path",
  "645": "Somapura Mahavihara",
  "646": "Saint Naum Monastery",
  "647": "Moscow Botanical Garden of Academy of Sciences",
  "648": "De Biesbosch",
  "649": "Secession Hall (Austria)",
  "650": "Gro%C3%9Fglockner-Hochalpenstra%C3%9Fe",
  "651": "Rax",
  "652": "Sky Meadows State Park",
  "653": "Altausseer See",
  "654": "Amberd",
  "655": "Fort Pulaski National Monument",
  "656": "Hungry Mother State Park",
  "657": "Cidade da Cultura",
  "658": "Muktinath",
  "659": "Saint Holy Mother church of Yeghvard",
  "660": "Buzkiy Gard National Nature Park",
  "661": "Fushimi Inari-taisha",
  "662": "Ch%C3%A2teau de Chinon",
  "663": "Hayravank monastery",
  "664": "East Side Gallery",
  "665": "Changdeokgung",
  "666": "Samuil's Fortress, Ohrid",
  "667": "Masada",
  "668": "Pragser Wildsee",
  "669": "Hautes Fagnes",
  "670": "Circuit Paul Armagnac",
  "671": "Banteay Srei",
  "672": "Naturschutzgebiet Schwarze Heide",
  "673": "Gettysburg National Military Park",
  "674": "Sabatini Gardens",
  "675": "Aterro do Flamengo",
  "676": "Exe Estuary",
  "677": "St. John of Mastara",
  "678": "Etchmiadzin Cathedral",
  "679": "Tajhat Palace",
  "680": "Roppongi",
  "681": "Prielbrusye",
  "682": "Saint John of God Church (San Rafael, Bulacan)",
  "683": "Esplanade Avenue, New Orleans",
  "684": "Industrial Canal",
  "685": "Ein Afek",
  "686": "Basilique Saint-Nicolas (Nantes)",
  "687": "National Museum, New Delhi",
  "688": "Fort St. Angelo",
  "689": "Kennet and Avon Canal",
  "690": "Vorontsovsky Palace (Crimea)",
  "691": "Rohtas Fort",
  "692": "Mehrauli Archaeological Park",
  "693": "Syretsky arboretum",
  "694": "Marmashen",
  "695": "Huis Doorn",
  "696": "Aguinaldo Shrine",
  "697": "B%C3%A1varo",
  "698": "Pidhirtsi Castle",
  "699": "%C5%A0arena D%C5%BEamija (Tetovo)",
  "700": "Baikove Cemetery",
  "701": "Ellora Caves",
  "702": "Izborsk Fortress",
  "703": "Lake Wendouree",
  "704": "Neam%C8%9B Citadel",
  "705": "Donostiako danborrada",
  "706": "Borgo medievale (Turin)",
  "707": "Jewish cemetery Prague-Josefov",
  "708": "Tortuguero National Park",
  "709": "Achilleion (Corfu)",
  "710": "Nature of Antarctica",
  "711": "Kykkos Monastery",
  "712": "Republic Square of Yerevan",
  "713": "Tower Bridge",
  "714": "Main Street, Gibraltar",
  "715": "Goshavank",
  "716": "Wan Chai",
  "717": "False Cape State Park",
  "718": "Lingnerschloss",
  "719": "Gion Matsuri",
  "720": "Port of Southampton",
  "721": "Suva Gora",
  "722": "Portsmouth Harbour",
  "723": "Holosiiv National Nature Park",
  "724": "Isle of Portland",
  "725": "Vank Cathedral",
  "726": "Botanischer Garten Erlangen",
  "727": "Tintern Abbey, Wales",
  "728": "Yungang Grottoes",
  "729": "Gran Paradiso National Park",
  "730": "Truskavets park",
  "731": "Baltimore Heritage",
  "732": "Lok Virsa Museum, Islamabad",
  "733": "Saint Hakob, Kanaker",
  "734": "Wittmoor",
  "735": "Pal%C3%A1cio Nacional da Pena",
  "736": "Caledon State Park",
  "737": "Meadowlark Botanical Gardens",
  "738": "Mera Peak",
  "739": "Falstad concentration camp",
  "740": "Museum of Oil and Gas Industry in B%C3%B3brka",
  "741": "Olsztyn Jura Castle",
  "742": "Mokolii",
  "743": "Rochester Castle",
  "744": "Brookwood Cemetery",
  "745": "Ch%C3%A2teau de Josselin",
  "746": "Smederevo Fortress",
  "747": "St. John Cathedral Church in Wroc%C5%82aw",
  "748": "Red Fort",
  "749": "Nyhavn",
  "750": "Imperial War Museum Duxford",
  "751": "Hampstead Heath",
  "752": "Archdiocesan Shrine of Saint Joseph the Patriarch of San Jose, Batangas",
  "753": "Ch%C3%A2teau de Bizy",
  "754": "So%C4%8Da",
  "755": "Mount Wutai",
  "756": "Phuket FantaSea",
  "757": "Popova %C5%A0apka",
  "758": "Elephantine",
  "759": "Saint Monica Parish Church in Minalin, Pampanga",
  "760": "Ol%C5%A1ansk%C3%A9 h%C5%99bitovy",
  "761": "Ibirapuera Park",
  "762": "Dubno Castle",
  "763": "Church of the Saviour on the Blood",
  "764": "Khreshchatyk",
  "765": "Summer Palace, Beijing",
  "766": "West Voe of Sumburgh",
  "767": "San Anton Palace",
  "768": "Nor Varagavank",
  "769": "Las Casas Filipinas de A%C3%A7%C3%BAzar",
  "770": "The Hague old City Hall",
  "771": "Chhatrapati Shivaji Terminus (formerly Victoria Terminus)",
  "772": "Trafalgar Square",
  "773": "Serra de Tramuntana",
  "774": "Acharya Jagadish Chandra Bose Indian Botanic Garden",
  "775": "Gali%C4%8Dica",
  "776": "Saint Hovhannes church of Kond",
  "777": "Parc de Saint-Cloud",
  "778": "Vorotnavank",
  "779": "Western Wall",
  "780": "Rhine Falls",
  "781": "Kara-Dag Nature Reserve",
  "782": "Parque Nacional de Jericoacoara",
  "783": "Harichavank",
  "784": "Svetitskhoveli",
  "785": "Shrine of the Immaculate Conception (Concepcion, Tarlac)",
  "786": "Chapada dos Veadeiros National Park",
  "787": "Parque Natural de Cabo de Gata-N%C3%ADjar",
  "788": "Batu Caves",
  "789": "Castle Doornenburg",
  "790": "Kur%C5%A1umli An",
  "791": "Jardim Bot%C3%A2nico de S%C3%A3o Paulo",
  "792": "%C3%89comus%C3%A9e d'Alsace",
  "793": "Neghuts Monastery",
  "794": "Kasteel Middachten",
  "795": "Midshires Way",
  "796": "Parkeisenbahn Cottbus",
  "797": "Grote of Lebu%C3%AFnuskerk",
  "798": "Persepolis",
  "799": "Our Lady of the Assumption Parish Church in Bulacan, Bulacan",
  "800": "Nuestra Se%C3%B1ora de Luj%C3%A1n Basilica",
  "801": "Shaniwar Wada",
  "802": "Annapurna Himal",
  "803": "Nizhny Novgorod",
  "804": "Muiderslot",
  "805": "Monaco-Ville",
  "806": "Saint Sarkis Cathedral, Yerevan",
  "807": "Maksym Rylsky Holosiiv park",
  "808": "Palacio de La Moneda",
  "809": "Bassin de la Villette",
  "810": "Government Museum (Bangalore)",
  "811": "Remise (transport museum)",
  "812": "Janskerk Hoorn (Terschelling)",
  "813": "Jaffa",
  "814": "Old City (Jerusalem)",
  "815": "Port of Jaffa",
  "816": "Krimml Waterfalls",
  "817": "Mount Rushmore National Memorial",
  "818": "Kiev Zoo",
  "819": "New River Trail State Park",
  "820": "Montgomery Canal",
  "821": "Hilbre Island",
  "822": "Louisbourg",
  "823": "Hoh Rain Forest",
  "824": "Huntley Meadows Park",
  "825": "Ratargul Swamp Forest",
  "826": "India Gate",
  "827": "Ch%C3%A2teau de Chenonceau",
  "828": "Cango Caves",
  "829": "Trinitatisfriedhof, Dresden",
  "830": "Museo del Ferrocarril (Madrid)",
  "831": "Mamshit",
  "832": "Aj-Petri",
  "833": "Lodi Gardens",
  "834": "Usina del Arte",
  "835": "Eiffel Tower",
  "836": "Vorontsovsky park",
  "837": "Mavrovo Lake",
  "838": "Bratislava Castle",
  "839": "Namib-Naukluft National Park",
  "840": "Museum Het Prinsenhof",
  "841": "Yerevan Ararat Wine Factory",
  "842": "Esta%C3%A7%C3%A3o da Luz",
  "843": "Las M%C3%A9dulas",
  "844": "Caverna do Diabo",
  "845": "Xishuangbanna Tropical Botanical Garden",
  "846": "Museum of Asian art of Corfu",
  "847": "Kiyomizu-dera",
  "848": "Sapieha Palace in Ru%C5%BEany",
  "849": "Schweriner Schloss",
  "850": "Recoleta Cemetery",
  "851": "Meycauayan Church",
  "852": "Humble Administrator's Garden",
  "853": "Victoria Memorial, London",
  "854": "V%C3%A5gen, Bergen",
  "855": "Moszna Castle",
  "856": "Lower Fort Garry",
  "857": "Shalimar Gardens (Lahore)",
  "858": "Oshki",
  "859": "Moku Manu",
  "860": "Golden Gate Park",
  "861": "Greensand Way",
  "862": "Kuwait Zoo",
  "863": "Kloster Michelsberg",
  "864": "Kilmainham Gaol",
  "865": "Australian National Botanic Gardens",
  "866": "Nederlands Openluchtmuseum",
  "867": "Surb Zoravor Astvatsatsin Church",
  "868": "Town Square (Ljubljana)",
  "869": "Parque de El Capricho",
  "870": "R%C3%B6mische Villa Haselburg",
  "871": "Embassy of the United States in Bangkok",
  "872": "Antonine baths (Carthage)",
  "873": "Aj-Petri Yayla",
  "874": "Siwa",
  "875": "Skopje Fortress",
  "876": "Santa Maria della Consolazione (Todi)",
  "877": "St. Andrew's Church, Kiev",
  "878": "Schloss Nordkirchen",
  "879": "Regierungsbunker",
  "880": "Hubbard Glacier",
  "881": "Sumburgh Head",
  "882": "Gloriette Sch%C3%B6nbrunn",
  "883": "Botanischer Garten der Universit%C3%A4t Basel",
  "884": "Saint Sargis Monastery of Ushi",
  "885": "Great Barrier Reef",
  "886": "S%C3%A4chsische Landesbibliothek %E2%80%93 Staats- und Universit%C3%A4tsbibliothek Dresden",
  "887": "NTUU KPI Polytechnic Museum",
  "888": "Durham Cathedral",
  "889": "Hunza Valley",
  "890": "Church of the Resurrection, Foros",
  "891": "National Botanical Garden of Bangladesh",
  "892": "Gardens by the Bay",
  "893": "Arroyo Burro Beach",
  "894": "West Norwood Cemetery",
  "895": "Statens historiska museum",
  "896": "Nikitsky Botanical Garden",
  "897": "Alexandra Palace",
  "898": "Parque Nacional do Pantanal Matogrossense",
  "899": "Convento de Santiago Ap%C3%B3stol, Cuilapam",
  "900": "Plaza de Mayo, Buenos Aires",
  "901": "Nottingham Canal",
  "902": "Campo Imperatore",
  "903": "Roanoke College",
  "904": "Theatro da Paz",
  "905": "Puente de Arganzuela, Madrid",
  "906": "Yunomine Onsen",
  "907": "Khosrov Forest State Reserve",
  "908": "Caernarfon Castle",
  "909": "Slava Park, Kiev",
  "910": "Colaba",
  "911": "Central, Hong Kong",
  "912": "Legoland Windsor",
  "913": "Machhapuchchhre",
  "914": "Houses on the National Register of Historic Places in Middlesex County, Massachusetts",
  "915": "Castles of Lastours",
  "916": "Udayagiri and Khandagiri Caves",
  "917": "Skansen",
  "918": "2018 US Open (tennis)",
  "919": "Kecharis",
  "920": "Catherine Park",
  "921": "Museu Catavento",
  "922": "Delicate Arch",
  "923": "Oriental Pearl Tower",
  "924": "Aptekarsky Ogorod",
  "925": "Bunhill Fields",
  "926": "Texas State Library and Archives Commission",
  "927": "Ponte Vasco da Gama",
  "928": "Museum of Folk Architecture and Life, Uzhhorod",
  "929": "Ilulissat",
  "930": "Skomer Island",
  "931": "Texas Renaissance Festival",
  "932": "Planes of Fame Air Museum",
  "933": "Zaryadye Park",
  "934": "Castelo de S%C3%A3o Jorge",
  "935": "Church of the Theotokos of the Sign (Dubrovitsy)",
  "936": "Rila National Park",
  "937": "Australian War Memorial",
  "938": "Schloss Johannisburg",
  "939": "Glen of Imaal",
  "940": "Cubao Cathedral",
  "941": "Moritzburg Castle",
  "942": "Potala Palace",
  "943": "Elberadweg",
  "944": "St. Laurentius und Vitus (Weinried)",
  "945": "Nuestra Se%C3%B1ora Del Pilar Parish Church (San Simon, Pampanga)",
  "946": "Chab%C3%B3wka railway museum",
  "947": "Friedhof Heerstra%C3%9Fe",
  "948": "Lahori Gate (Red Fort)",
  "949": "Pocahontas State Park",
  "950": "%C4%8Cesk%C3%BD Krumlov Castle",
  "951": "Uspenski Cathedral",
  "952": "Smith Mountain Lake State Park",
  "953": "Templo Zu Lai",
  "954": "Mercado de Col%C3%B3n",
  "955": "Mulkey Cemetery",
  "956": "Subterranean Skansen Guido",
  "957": "Glasnevin Cemetery",
  "958": "Death Valley National Park",
  "959": "Frecce Tricolori",
  "960": "Wadi Degla",
  "961": "Mus%C3%A9e Rodin",
  "962": "Templo de Diana (%C3%89vora)",
  "963": "Saint Peter Church (Woerden)",
  "964": "Oudegracht",
  "965": "Eram Garden",
  "966": "Ek' balam",
  "967": "Cmentarz Prawos%C5%82awny na Woli",
  "968": "Mustafa Pasha Mosque (Skopje)",
  "969": "Alexander Stream",
  "970": "Crimean Mountains",
  "971": "River Tees",
  "972": "J%C3%B6kuls%C3%A1rl%C3%B3n",
  "973": "Didcot Railway Centre",
  "974": "White Tower (Thessaloniki)",
  "975": "Frontenpark (Maastricht)",
  "976": "Abraham Lincoln seated at the Lincoln Memorial",
  "977": "Parc d%C3%A9partemental Georges-Valbon",
  "978": "Musrara",
  "979": "2018 Toronto International Film Festival",
  "980": "Montju%C3%AFc Cemetery",
  "981": "Bulevar de Sabana Grande",
  "982": "Kr%C3%A4merbr%C3%BCcke (Erfurt)",
  "983": "Gda%C5%84sk Shipyard",
  "984": "Zhovkva Castle",
  "985": "Rocca di Imola",
  "986": "Acropolis of Lindos",
  "987": "Leineaue zwischen Ruthe und Koldingen",
  "988": "W%C3%B6rthersee",
  "989": "Sailor's Creek Battlefield Historical State Park",
  "990": "Jardin japonais, Toulouse",
  "991": "Old Town Square (Prague)",
  "992": "Stob pyramids",
  "993": "De Slufter",
  "994": "Sviatohirsk Lavra",
  "995": "Vvedenskoe cemetery",
  "996": "Cave of the Patriarchs",
  "997": "Gullfoss",
  "998": "Torre dos Cl%C3%A9rigos",
  "999": "Pennine Way",
  "1000": "Story Bridge, Brisbane",
  "1001": "Pallas Athena statue, Vienna",
  "1002": "Cardiff Bay",
  "1003": "Petroglyphs in the Edakkal Caves",
  "1004": "Lviv Opera House",
  "1005": "Naturschutzgebiet Mastberg und Innersteaue",
  "1006": "Saxon Shore Way",
  "1007": "Brooklyn Bridge",
  "1008": "Huis Bergh",
  "1009": "Milford Sound",
  "1010": "Monument Valley",
  "1011": "Taal Basilica",
  "1012": "Temple of Venus and Rome (Rome)",
  "1013": "Sydney Opera House",
  "1014": "Hovhannavank Monastery",
  "1015": "Sensoji",
  "1016": "Dai Anga Tomb, Lahore",
  "1017": "Katasraj temple",
  "1018": "Sint Elisabethskerk, Grave",
  "1019": "Simon en Judaskerk (Ootmarsum)",
  "1020": "Village Museum, Bucharest",
  "1021": "Tidersrums kyrka",
  "1022": "Saint Stepanos Monastery",
  "1023": "Tsumago-juku",
  "1024": "Dihua Street",
  "1025": "Cheongwadae",
  "1026": "Hyde Park, London",
  "1027": "Kivikko",
  "1028": "2018 University Boat Race",
  "1029": "Whitby Abbey",
  "1030": "Westminster Bridge",
  "1031": "Hanuman Dhoka",
  "1032": "Illeta dels Banyets",
  "1033": "Bled Castle",
  "1034": "Flumserberg",
  "1035": "Lake Ohrid",
  "1036": "Iguazu Falls",
  "1037": "Peizazhna Alley",
  "1038": "Castillo de los Tres Reyes del Morro",
  "1039": "Raglan Castle",
  "1040": "Itatiaia National Park",
  "1041": "Royal Botanic Garden Edinburgh",
  "1042": "Cemit%C3%A9rio dos Prazeres",
  "1043": "St. Michael's Golden-Domed Monastery in Kiev",
  "1044": "Sevan National Park",
  "1045": "Tyne Bridge",
  "1046": "Torrione prenestino (Rome)",
  "1047": "Taras Shevchenko Park, Kiev",
  "1048": "Old Town of Lijiang",
  "1049": "Theatro Municipal (Rio de Janeiro)",
  "1050": "Berlin Wall",
  "1051": "Altmarkt, Dresden",
  "1052": "D%C3%BAn Laoghaire",
  "1053": "Malostransk%C3%A1 mosteck%C3%A1 v%C4%9B%C5%BE",
  "1054": "Wat Arun",
  "1055": "Deutsches Landwirtschaftsmuseum",
  "1056": "Banff National Park",
  "1057": "Kapellbr%C3%BCcke",
  "1058": "Adalaj Stepwell",
  "1059": "Baixa Pombalina",
  "1060": "Besucherbergwerk Abraumf%C3%B6rderbr%C3%BCcke F60",
  "1061": "Palacio Legislativo, Uruguay",
  "1062": "Pra%C5%A1n%C3%A1 br%C3%A1na",
  "1063": "Pairi Daiza",
  "1064": "Bet Shearim",
  "1065": "Jabel Jais",
  "1066": "John Muir Wilderness",
  "1067": "Hanging Temple",
  "1068": "Market Square, Lviv",
  "1069": "Saint James the Greater Church (Plaridel, Bulacan)",
  "1070": "Waag (Alkmaar)",
  "1071": "Kawayu Onsen (Wakayama)",
  "1072": "Park Miniatur w Inwa%C5%82dzie",
  "1073": "Lake Bohinj",
  "1074": "Schloss Seehof",
  "1075": "Waalsdorpervlakte",
  "1076": "Haapsalu Castle",
  "1077": "Mount of Olives",
  "1078": "Hoover Dam",
  "1079": "The Great Canyon of Crimea",
  "1080": "Bellu Cemetery",
  "1081": "Suomenlinna",
  "1082": "Offa's Dyke Path",
  "1083": "River Trent",
  "1084": "Museo Arqueol%C3%B3gico Rafael Larco Herrera",
  "1085": "%C4%86elije Monastery",
  "1086": "Grote of Onze-Lieve-Vrouwekerk (Dordrecht)",
  "1087": "S%C3%A4chsisches Eisenbahnmuseum",
  "1088": "West Lake",
  "1089": "Ghirlandina (Modena)",
  "1090": "Altenburg (Bamberg)",
  "1091": "Loschwitzer Friedhof",
  "1092": "Luray Caverns",
  "1093": "Pacific Aviation Museum",
  "1094": "R%C3%A2%C8%99nov Castle",
  "1095": "Fisherman's Wharf, San Francisco",
  "1096": "Golra Sharif Railway Museum",
  "1097": "Pirin National Park",
  "1098": "Ancient Roman walls of Lugo",
  "1099": "Wolfsschanze",
  "1100": "Hrad%C4%8Dansk%C3%A9 n%C3%A1m%C4%9Bst%C3%AD",
  "1101": "Scottish Parliament Building",
  "1102": "Tarka Trail",
  "1103": "St%C3%BCbing",
  "1104": "City Park, New Orleans",
  "1105": "Wilderness Road State Park",
  "1106": "Bosque de la Rep%C3%BAblica",
  "1107": "National Museum of Anthropology",
  "1108": "Puthia Rajbari",
  "1109": "Timmelsjoch",
  "1110": "Nazca lines",
  "1111": "Ajanta Caves",
  "1112": "Noravank",
  "1113": "Tulum",
  "1114": "Valle de la Orotava",
  "1115": "Briloner Eisenberg",
  "1116": "St Walburgis Church (Zutphen)",
  "1117": "Parco naturale provinciale dell'Adamello-Brenta",
  "1118": "Holy Saviour Church, Gyumri",
  "1119": "Novyi Svit Sanctuary",
  "1120": "Victoria Memorial, Kolkata",
  "1121": "Kaniv Nature Reserve",
  "1122": "Osogovo Monastery",
  "1123": "Kapan an",
  "1124": "Old City Walls (Jerusalem)",
  "1125": "Wichita Mountains Wildlife Refuge",
  "1126": "Yellowstone National Park",
  "1127": "Lake Constance",
  "1128": "Tatev",
  "1129": "Barasoain Church",
  "1130": "SoHo, Manhattan",
  "1131": "Eugene Masonic Cemetery",
  "1132": "Museo de Arte Precolombino, Cusco",
  "1133": "Zlatibor",
  "1134": "Aruchavank",
  "1135": "Wat Mahathat (Sukhothai)",
  "1136": "Lulworth Cove, Dorset",
  "1137": "Hundertwasserhaus Wien",
  "1138": "Floor mosaics in Freiburg im Breisgau, Germany",
  "1139": "Porto de Galinhas",
  "1140": "Kelaniya Raja Maha Vihara",
  "1141": "St. Martin (Tussenhausen)",
  "1142": "Citadel of Erbil",
  "1143": "Centro Hist%C3%B3rico de Tunja",
  "1144": "Prague Astronomical Clock",
  "1145": "Walls of %C3%81vila",
  "1146": "Kobayr",
  "1147": "Windermere",
  "1148": "2017 Toronto International Film Festival",
  "1149": "Royal Albert Dock, Liverpool",
  "1150": "River Clyde",
  "1151": "Ny Carlsberg Glyptotek",
  "1152": "Snizort",
  "1153": "S%C3%A9 (S%C3%A3o Paulo)",
  "1154": "Len%C3%A7%C3%B3is Maranhenses",
  "1155": "Centro Cultural Metropolitano",
  "1156": "Ben Nevis",
  "1157": "Dark Divide",
  "1158": "Camp Nou",
  "1159": "Cementerio General de Santiago",
  "1160": "Swallow's Nest (Crimea)",
  "1161": "Tomb of Safdarjung",
  "1162": "Bouzov Castle",
  "1163": "Lotus Temple",
  "1164": "Synevyr National Nature Park",
  "1165": "Finger Lakes Trail",
  "1166": "Kissimmee Air Museum",
  "1167": "Treska",
  "1168": "Ricetto di Candelo",
  "1169": "National Flag Memorial",
  "1170": "Naturschutzgebiet Hohenstein",
  "1171": "John F. Kennedy Center for the Performing Arts",
  "1172": "Villa Durazzo Pallavicini (Genoa)",
  "1173": "Lake Lugano",
  "1174": "Mount Emei",
  "1175": "Shandong",
  "1176": "Nationalpark Schleswig-Holsteinisches Wattenmeer",
  "1177": "Nikiszowiec",
  "1178": "Parliament House, Canberra",
  "1179": "Saint Sargis, Ashtarak",
  "1180": "Colonial Williamsburg",
  "1181": "High Weald Landscape Trail",
  "1182": "Shivapuri Nagarjun National Park",
  "1183": "Bastei",
  "1184": "Lake Burrumbeet",
  "1185": "Llotja de la Seda",
  "1186": "Marienstiftskirche Lich",
  "1187": "Valkenburg Castle",
  "1188": "Pechersky Monastery (Nizhny Novgorod)",
  "1189": "Room 95, British Museum",
  "1190": "Church of Saints Olga and Elizabeth, Lviv",
  "1191": "Funa fortress",
  "1192": "Padr%C3%A3o dos Descobrimentos",
  "1193": "Sossusvlei",
  "1194": "Ergaki",
  "1195": "Masoudieh Mansion",
  "1196": "Kinkaku-ji",
  "1197": "Cemetery H%C3%A1zsong%C3%A1rd",
  "1198": "Fairfield Showground",
  "1199": "Kolomna Kremlin",
  "1200": "Pra%C3%A7a de D. Pedro IV",
  "1201": "Kasteel Duivenvoorde",
  "1202": "Klosterkirche St. Annen (Kamenz)",
  "1203": "Dorotheenst%C3%A4dtischer Friedhof",
  "1204": "Belintash",
  "1205": "New Town Hall (Munich)",
  "1206": "Vecr%C4%ABga",
  "1207": "Malostransk%C3%A9 n%C3%A1m%C4%9Bst%C3%AD (Prague)",
  "1208": "Abtei Plankstetten",
  "1209": "Saint John's Cathedral, 's-Hertogenbosch",
  "1210": "Transfiguration monastery (Murom)",
  "1211": "Saint Sophia Cathedral in Kiev",
  "1212": "California",
  "1213": "Parque Ecol%C3%B3gico de Xochimilco",
  "1214": "Faisal Mosque",
  "1215": "Blue Wonder",
  "1216": "Yuyuan Gardens",
  "1217": "St. James's Park",
  "1218": "Evangelical-Reformed Cemetery in Warsaw",
  "1219": "Pamukkale",
  "1220": "Picos de Europa",
  "1221": "Zugspitze",
  "1222": "Neva River",
  "1223": "Dyrham Park",
  "1224": "Mont Blanc",
  "1225": "Ports de Tortosa Beseit",
  "1226": "Trakai Island Castle",
  "1227": "P%C3%A1l-v%C3%B6lgy Cave",
  "1228": "Abbey, Middelburg",
  "1229": "Festung Rosenberg",
  "1230": "Naturschutzgebiet Steinberg bei Wesseln",
  "1231": "Chattahoochee-Oconee National Forest",
  "1232": "Her%C4%83str%C4%83u",
  "1233": "Novodevichy Convent",
  "1234": "Heskin Hall",
  "1235": "Jardin botanique de Montr%C3%A9al",
  "1236": "Borujerdis House",
  "1237": "Huize Ruurlo",
  "1238": "Naturschutzgebiet Steinbruch Holzm%C3%BChle",
  "1239": "Soreq Cave",
  "1240": "Beverley Minster",
  "1241": "St. Sophia Church (Ohrid)",
  "1242": "Cabo da Roca",
  "1243": "Gournia",
  "1244": "Giardino Botanico Alpino Viote",
  "1245": "Studenica Monastery",
  "1246": "Hawa Mahal",
  "1247": "Giant Wild Goose Pagoda",
  "1248": "Crusaders' Halls",
  "1249": "Castle Ammersoyen",
  "1250": "Parc Natural de Collserola",
  "1251": "Vesting Bourtange",
  "1252": "Lokrum",
  "1253": "Warta",
  "1254": "Strandbad Tiefenbrunnen",
  "1255": "Shypit Waterfall",
  "1256": "Chinatown, Yokohama",
  "1257": "Candi Panataran",
  "1258": "Ein Gedi",
  "1259": "Biblioteca Nacional de Espa%C3%B1a",
  "1260": "Karlskirche, Vienna",
  "1261": "Sawtooth Range",
  "1262": "Marina City",
  "1263": "Ruskin Park",
  "1264": "Nature Reserve Chalkland flora",
  "1265": "Schw%C3%A4bische Alb",
  "1266": "Eiktunet",
  "1267": "Grand Palace, Bangkok",
  "1268": "Honey Island Swamp",
  "1269": "Caesarea Maritima",
  "1270": "Uspensky monastery in Bakhchisaray",
  "1271": "South Beach",
  "1272": "Harbour of Oslo",
  "1273": "Sint-Lambertuskerk (Buren)",
  "1274": "Mitla",
  "1275": "Kashueti Church",
  "1276": "Jewish cemetery in Cz%C4%99stochowa",
  "1277": "Medzhybizh Castle",
  "1278": "Walderveense molen",
  "1279": "Bangabandhu Sheikh Mujib Safari Park",
  "1280": "Mini-Europe",
  "1281": "Evangelische Pfarrkirche M%C3%BCnzenberg",
  "1282": "Carrie Furnace",
  "1283": "Rizal Park",
  "1284": "Amman Citadel",
  "1285": "Wieliczka salt mine",
  "1286": "Petronas Towers",
  "1287": "Bolingbroke Castle",
  "1288": "Stora Sj%C3%B6fallet National Park",
  "1289": "Lingehaven",
  "1290": "Du Fu Thatched Cottage",
  "1291": "Titisee",
  "1292": "Augustusbr%C3%BCcke",
  "1293": "Museum of Icons in Supra%C5%9Bl",
  "1294": "Troekurovo Cemetery",
  "1295": "Aysgarth Falls",
  "1296": "The Embarcadero (San Francisco)",
  "1297": "Sacsayhuam%C3%A1n",
  "1298": "Port of Vigo",
  "1299": "Poblenou Cemetery",
  "1300": "Saint Hilarion Castle",
  "1301": "Jog Falls",
  "1302": "Ein Avdat",
  "1303": "Washington Monument",
  "1304": "Marine Corps Base Camp Pendleton",
  "1305": "M%C4%81nana",
  "1306": "Parc du Premier-Chemin-de-Fer",
  "1307": "Lulusar Lake",
  "1308": "Geirangerfjorden",
  "1309": "Botanical gardens in Meran",
  "1310": "Orheiul Vechi",
  "1311": "Yeltsin Center",
  "1312": "Zuiderkerk (Enkhuizen)",
  "1313": "Ukrainian Air Force Museum in Vinnytsya",
  "1314": "Pangong Tso",
  "1315": "Mari%C3%A4 Himmelfahrt (Mattsies)",
  "1316": "Saint Demetrius Church (Vladimir)",
  "1317": "Sequoia National Park",
  "1318": "Krylatsky Hills",
  "1319": "St. Paul the First Hermit Cathedral",
  "1320": "Ma Tau Wai",
  "1321": "Yosemite Valley",
  "1322": "Seney National Wildlife Refuge",
  "1323": "Teletskoye Lake",
  "1324": "Tikal",
  "1325": "Bukittinggi",
  "1326": "National Museum of the Philippines",
  "1327": "Temple of Poseidon at Cape Sounion",
  "1328": "Vers%C3%B6hnungskirche (Dresden)",
  "1329": "St. Michael the Archangel Church (Avtokomanda)",
  "1330": "Dashtadem fortress",
  "1331": "Ouzoud Falls",
  "1332": "Cradle Mountain",
  "1333": "Z%C3%BCrichhorn",
  "1334": "Terminal Tower",
  "1335": "De tuinen van Mien Ruys",
  "1336": "Palace of Westminster",
  "1337": "DASA %E2%80%93 Arbeitswelt Ausstellung",
  "1338": "Mission Santa Barbara",
  "1339": "Ponta da Piedade",
  "1340": "Sint-Gertrudiskerk (Bergen op Zoom)",
  "1341": "Certosa di Pisa",
  "1342": "Hennetalsperre",
  "1343": "Centennial Park, Sydney",
  "1344": "Beamish Museum",
  "1345": "Museu de Prehist%C3%B2ria de Val%C3%A8ncia",
  "1346": "Basilica Cistern of Constantinople",
  "1347": "Old Slave Lodge, Cape Town",
  "1348": "Pyatnytska Church (Chernihiv)",
  "1349": "St Deiniol's Church, Hawarden",
  "1350": "Uxmal - Pir%C3%A1mide del Adivino",
  "1351": "Rila",
  "1352": "Schloss Solitude",
  "1353": "Carnegie Museum of Natural History",
  "1354": "Vasquez Rocks Natural Area Park",
  "1355": "Schoenborn Palace",
  "1356": "%C4%8Cifte Amam",
  "1357": "Soviet War Memorial (Treptower Park)",
  "1358": "Piney Run Park",
  "1359": "Old City Hall, Boston",
  "1360": "Lake Kerkini",
  "1361": "Santa Chiara (Naples)",
  "1362": "Ayu-Dag",
  "1363": "Georgian National Museum",
  "1364": "Aiguille du Midi",
  "1365": "Fountains Abbey",
  "1366": "George Washington Bridge",
  "1367": "Parkanlage Vorwerk",
  "1368": "Illas C%C3%ADes",
  "1369": "Janaki Mandir",
  "1370": "Posters",
  "1371": "Lake Sampaloc",
  "1372": "S%C3%BCmeg Castle",
  "1373": "Zhaojiabao",
  "1374": "York railway station",
  "1375": "St Stevenskerk (Nijmegen)",
  "1376": "Saint Louis of Toulouse Parish Church of Lucban",
  "1377": "Kiasma",
  "1378": "Llanfair-ar-y-bryn",
  "1379": "Praia da Nazar%C3%A9",
  "1380": "St. David's Bishop's Palace",
  "1381": "Prinzipalmarkt",
  "1382": "Castello di Popoli",
  "1383": "Boleyn Ground",
  "1384": "Fairy Stone State Park",
  "1385": "Petra, Jordan",
  "1386": "Starom%C4%9Bstsk%C3%A1 mosteck%C3%A1 v%C4%9B%C5%BE",
  "1387": "Agamon HaHula",
  "1388": "Plymouth Sound",
  "1389": "Geisler group",
  "1390": "Caves of Saint Anthony in Chernihiv",
  "1391": "Wade Park (Cleveland)",
  "1392": "Frere Hall",
  "1393": "Ternopil Pond",
  "1394": "Scott Monument",
  "1395": "IJsselmeer",
  "1396": "Newark Air Museum",
  "1397": "Wat Yannawa",
  "1398": "Shushtar Historical Hydraulic System",
  "1399": "Oude Maas",
  "1400": "Wat Si Saket",
  "1401": "Belvoir Fortress",
  "1402": "Aquarium Finisterrae",
  "1403": "Bamburgh Castle",
  "1404": "Oriole Park at Camden Yards",
  "1405": "Saint-Henri",
  "1406": "Green Lawn Cemetery, Columbus, Ohio",
  "1407": "The Jordan Museum",
  "1408": "Kong Meng San Phor Kark See Monastery",
  "1409": "Hula Valley",
  "1410": "Glen Coe",
  "1411": "Tomb of Ali Mardan Khan",
  "1412": "Ch%C3%A2teau de Chambord",
  "1413": "Museum Europ%C3%A4ischer Kulturen",
  "1414": "Jardins del Real de Val%C3%A8ncia",
  "1415": "Judean Desert",
  "1416": "Dresden Castle",
  "1417": "Sundarbans National Park",
  "1418": "Monumento ai caduti (Ancona)",
  "1419": "King Street Station (Seattle)",
  "1420": "Saint John the Baptist church, Cirencester",
  "1421": "Tatevi Anapat",
  "1422": "Michelangelo's Moses",
  "1423": "International Museum of Ceramics in Faenza",
  "1424": "Slot Haamstede",
  "1425": "Hoensbroek Castle",
  "1426": "Tj%C3%B6rnin",
  "1427": "Rio de Janeiro Olympic Park",
  "1428": "L'Umbracle",
  "1429": "Mondo Verde, Landgraaf",
  "1430": "Ir. D.F. Wouda-gemaal",
  "1431": "G%C3%B6yg%C3%B6l National Park",
  "1432": "Chinatown, Manhattan",
  "1433": "Tomb of Nur Jahan"
}